Metadata-Version: 2.1
Name: BetaBoost
Version: 0.0.5
Summary: BetaBoosting: gradient boosting with a beta function.
Home-page: https://github.com/tblume1992/BetaBoost
Author: Tyler Blume
Author-email: tblume@mail.USF.edu
License: UNKNOWN
Keywords: xgboost,gradient boosting,data science,machine learning
Platform: UNKNOWN
Classifier: Programming Language :: Python :: 3
Classifier: License :: OSI Approved :: MIT License
Classifier: Operating System :: OS Independent
